hack4u/__init__.py
hack4u/courses.py
hack4u/utils.py
xChrisxY-0.1.0.dist-info/METADATA
xChrisxY-0.1.0.dist-info/WHEEL
xChrisxY-0.1.0.dist-info/top_level.txt
xChrisxY-0.1.0.dist-info/RECORD
